{"meta": {"imageSize": {"width": 1150, "height": 1600}, "voca": "bert-base-uncased", "image_path": "training_data/images/VAIPE_P_TRAIN_672.png"}, "words": [{"text": "Điện", "tokens": [1102, 9013], "boundingBox": [[42, 105], [119, 105], [119, 140], [42, 140]]}, {"text": "thoại:", "tokens": [27793, 4886, 1024], "boundingBox": [[119, 105], [196, 105], [196, 140], [119, 140]]}, {"text": "ĐƠN", "tokens": [1102, 2239], "boundingBox": [[397, 150], [514, 150], [514, 192], [397, 192]]}, {"text": "THUỐC", "tokens": [16215, 19098, 2278], "boundingBox": [[514, 150], [631, 150], [631, 192], [514, 192]]}, {"text": "BHYT", "tokens": [1038, 10536, 2102], "boundingBox": [[631, 150], [748, 150], [748, 192], [631, 192]]}, {"text": "Cân", "tokens": [2064], "boundingBox": [[702, 215], [767, 215], [767, 250], [702, 250]]}, {"text": "nặng", "tokens": [16660, 2290], "boundingBox": [[767, 215], [832, 215], [832, 250], [767, 250]]}, {"text": "kg", "tokens": [4705], "boundingBox": [[832, 215], [897, 215], [897, 250], [832, 250]]}, {"text": "nam", "tokens": [15125], "boundingBox": [[897, 215], [962, 215], [962, 250], [897, 250]]}, {"text": "Nữ", "tokens": [16371], "boundingBox": [[1012, 215], [1057, 215], [1057, 242], [1012, 242]]}, {"text": "Chẩn", "tokens": [9212], "boundingBox": [[37, 349], [102, 349], [102, 393], [37, 393]]}, {"text": "đoán:", "tokens": [1102, 10441, 2078, 1024], "boundingBox": [[102, 349], [167, 349], [167, 393], [102, 393]]}, {"text": "L20", "tokens": [1048, 11387], "boundingBox": [[167, 349], [232, 349], [232, 393], [167, 393]]}, {"text": "-", "tokens": [1011], "boundingBox": [[232, 349], [297, 349], [297, 393], [232, 393]]}, {"text": "Viêm", "tokens": [20098, 2213], "boundingBox": [[297, 349], [362, 349], [362, 393], [297, 393]]}, {"text": "da", "tokens": [4830], "boundingBox": [[362, 349], [427, 349], [427, 393], [362, 393]]}, {"text": "cơ", "tokens": [2522], "boundingBox": [[427, 349], [492, 349], [492, 393], [427, 393]]}, {"text": "địa;", "tokens": [1102, 2401, 1025], "boundingBox": [[492, 349], [557, 349], [557, 393], [492, 393]]}, {"text": "(M13.0)", "tokens": [1006, 23290, 2509, 1012, 1014, 1007], "boundingBox": [[557, 349], [622, 349], [622, 393], [557, 393]]}, {"text": "Viêm", "tokens": [20098, 2213], "boundingBox": [[622, 349], [687, 349], [687, 393], [622, 393]]}, {"text": "đa", "tokens": [1102, 2050], "boundingBox": [[687, 349], [752, 349], [752, 393], [687, 393]]}, {"text": "khớp", "tokens": [1047, 18471], "boundingBox": [[752, 349], [817, 349], [817, 393], [752, 393]]}, {"text": "không", "tokens": [1047, 19991], "boundingBox": [[817, 349], [882, 349], [882, 393], [817, 393]]}, {"text": "đặc", "tokens": [1102, 6305], "boundingBox": [[882, 349], [947, 349], [947, 393], [882, 393]]}, {"text": "hiệu", "tokens": [7632, 13765], "boundingBox": [[947, 349], [1012, 349], [1012, 393], [947, 393]]}, {"text": "vai", "tokens": [12436, 2072], "boundingBox": [[1012, 349], [1077, 349], [1077, 393], [1012, 393]]}, {"text": "trái;", "tokens": [19817, 4886, 1025], "boundingBox": [[34, 386], [103, 386], [103, 432], [34, 432]]}, {"text": "(H81)", "tokens": [1006, 1044, 2620, 2487, 1007], "boundingBox": [[103, 386], [172, 386], [172, 432], [103, 432]]}, {"text": "Rối", "tokens": [25223], "boundingBox": [[172, 386], [241, 386], [241, 432], [172, 432]]}, {"text": "loạn", "tokens": [5414], "boundingBox": [[241, 386], [310, 386], [310, 432], [241, 432]]}, {"text": "chức", "tokens": [14684, 2278], "boundingBox": [[310, 386], [379, 386], [379, 432], [310, 432]]}, {"text": "năng", "tokens": [16660, 2290], "boundingBox": [[379, 386], [448, 386], [448, 432], [379, 432]]}, {"text": "tiền", "tokens": [5495, 2078], "boundingBox": [[448, 386], [517, 386], [517, 432], [448, 432]]}, {"text": "đình;", "tokens": [1102, 2378, 2232, 1025], "boundingBox": [[517, 386], [586, 386], [586, 432], [517, 432]]}, {"text": "(L50)", "tokens": [1006, 1048, 12376, 1007], "boundingBox": [[586, 386], [655, 386], [655, 432], [586, 432]]}, {"text": "Mày", "tokens": [2089], "boundingBox": [[655, 386], [724, 386], [724, 432], [655, 432]]}, {"text": "đay", "tokens": [1102, 4710], "boundingBox": [[724, 386], [793, 386], [793, 432], [724, 432]]}, {"text": "Thuốc", "tokens": [16215, 19098, 2278], "boundingBox": [[37, 428], [105, 428], [105, 470], [37, 470]]}, {"text": "điều", "tokens": [1102, 17301], "boundingBox": [[105, 428], [173, 428], [173, 470], [105, 470]]}, {"text": "trị:", "tokens": [13012, 1024], "boundingBox": [[173, 428], [241, 428], [241, 470], [173, 470]]}, {"text": "1)", "tokens": [1015, 1007], "boundingBox": [[37, 477], [132, 477], [132, 520], [37, 520]]}, {"text": "Cefalexin", "tokens": [8292, 7011, 2571, 20303], "boundingBox": [[132, 477], [227, 477], [227, 520], [132, 520]]}, {"text": "(Firstlexin", "tokens": [1006, 2034, 2571, 20303], "boundingBox": [[227, 477], [322, 477], [322, 520], [227, 520]]}, {"text": "500)", "tokens": [3156, 1007], "boundingBox": [[322, 477], [417, 477], [417, 520], [322, 520]]}, {"text": "0,5g", "tokens": [1014, 1010, 1019, 2290], "boundingBox": [[417, 477], [512, 477], [512, 520], [417, 520]]}, {"text": "Uống:", "tokens": [1057, 5063, 1024], "boundingBox": [[282, 544], [343, 544], [343, 587], [282, 587]]}, {"text": "Sáng", "tokens": [6369], "boundingBox": [[343, 544], [404, 544], [404, 587], [343, 587]]}, {"text": "2", "tokens": [1016], "boundingBox": [[404, 544], [465, 544], [465, 587], [404, 587]]}, {"text": "Viên", "tokens": [20098, 2078], "boundingBox": [[465, 544], [526, 544], [526, 587], [465, 587]]}, {"text": "Chiều", "tokens": [9610, 13765], "boundingBox": [[526, 544], [587, 544], [587, 587], [526, 587]]}, {"text": "2", "tokens": [1016], "boundingBox": [[587, 544], [648, 544], [648, 587], [587, 587]]}, {"text": "Viên", "tokens": [20098, 2078], "boundingBox": [[648, 544], [709, 544], [709, 587], [648, 587]]}, {"text": "Tối", "tokens": [2000, 2072], "boundingBox": [[709, 544], [770, 544], [770, 587], [709, 587]]}, {"text": "2", "tokens": [1016], "boundingBox": [[770, 544], [831, 544], [831, 587], [770, 587]]}, {"text": "Viên", "tokens": [20098, 2078], "boundingBox": [[831, 544], [892, 544], [892, 587], [831, 587]]}, {"text": "SL:", "tokens": [22889, 1024], "boundingBox": [[42, 550], [93, 550], [93, 577], [42, 577]]}, {"text": "30", "tokens": [2382], "boundingBox": [[93, 550], [144, 550], [144, 577], [93, 577]]}, {"text": "Viên", "tokens": [20098, 2078], "boundingBox": [[144, 550], [195, 550], [195, 577], [144, 577]]}, {"text": "2)", "tokens": [1016, 1007], "boundingBox": [[34, 605], [147, 605], [147, 647], [34, 647]]}, {"text": "Loxoprofen", "tokens": [8840, 2595, 7361, 3217, 18940], "boundingBox": [[147, 605], [260, 605], [260, 647], [147, 647]]}, {"text": "(Mezafen)", "tokens": [1006, 2033, 4143, 18940, 1007], "boundingBox": [[260, 605], [373, 605], [373, 647], [260, 647]]}, {"text": "60mg", "tokens": [3438, 24798], "boundingBox": [[373, 605], [486, 605], [486, 647], [373, 647]]}, {"text": "Uống:", "tokens": [1057, 5063, 1024], "boundingBox": [[282, 674], [343, 674], [343, 712], [282, 712]]}, {"text": "Sáng", "tokens": [6369], "boundingBox": [[343, 674], [404, 674], [404, 712], [343, 712]]}, {"text": "1", "tokens": [1015], "boundingBox": [[404, 674], [465, 674], [465, 712], [404, 712]]}, {"text": "Viên", "tokens": [20098, 2078], "boundingBox": [[465, 674], [526, 674], [526, 712], [465, 712]]}, {"text": "Chiều", "tokens": [9610, 13765], "boundingBox": [[526, 674], [587, 674], [587, 712], [526, 712]]}, {"text": "1", "tokens": [1015], "boundingBox": [[587, 674], [648, 674], [648, 712], [587, 712]]}, {"text": "Viên", "tokens": [20098, 2078], "boundingBox": [[648, 674], [709, 674], [709, 712], [648, 712]]}, {"text": "Tối", "tokens": [2000, 2072], "boundingBox": [[709, 674], [770, 674], [770, 712], [709, 712]]}, {"text": "1", "tokens": [1015], "boundingBox": [[770, 674], [831, 674], [831, 712], [770, 712]]}, {"text": "Viên", "tokens": [20098, 2078], "boundingBox": [[831, 674], [892, 674], [892, 712], [831, 712]]}, {"text": "SL:", "tokens": [22889, 1024], "boundingBox": [[42, 677], [93, 677], [93, 707], [42, 707]]}, {"text": "30", "tokens": [2382], "boundingBox": [[93, 677], [144, 677], [144, 707], [93, 707]]}, {"text": "Viên", "tokens": [20098, 2078], "boundingBox": [[144, 677], [195, 677], [195, 707], [144, 707]]}, {"text": "3)", "tokens": [1017, 1007], "boundingBox": [[37, 728], [122, 728], [122, 777], [37, 777]]}, {"text": "Đinh", "tokens": [1102, 2378, 2232], "boundingBox": [[122, 728], [207, 728], [207, 777], [122, 777]]}, {"text": "lăng,", "tokens": [11374, 1010], "boundingBox": [[207, 728], [292, 728], [292, 777], [207, 777]]}, {"text": "bạch", "tokens": [10384], "boundingBox": [[292, 728], [377, 728], [377, 777], [292, 777]]}, {"text": "quả", "tokens": [24209, 2050], "boundingBox": [[377, 728], [462, 728], [462, 777], [377, 777]]}, {"text": "(Hoạt", "tokens": [1006, 7570, 4017], "boundingBox": [[462, 728], [547, 728], [547, 777], [462, 777]]}, {"text": "huyết", "tokens": [15876, 6672, 2102], "boundingBox": [[547, 728], [632, 728], [632, 777], [547, 777]]}, {"text": "dưỡng", "tokens": [6829, 3070], "boundingBox": [[632, 728], [717, 728], [717, 777], [632, 777]]}, {"text": "não)", "tokens": [6583, 2080, 1007], "boundingBox": [[717, 728], [802, 728], [802, 777], [717, 777]]}, {"text": "150mg+20mg", "tokens": [5018, 24798, 1009, 2322, 24798], "boundingBox": [[802, 728], [887, 728], [887, 777], [802, 777]]}, {"text": "Uống:", "tokens": [1057, 5063, 1024], "boundingBox": [[282, 802], [341, 802], [341, 842], [282, 842]]}, {"text": "Sáng", "tokens": [6369], "boundingBox": [[341, 802], [400, 802], [400, 842], [341, 842]]}, {"text": "3", "tokens": [1017], "boundingBox": [[400, 802], [459, 802], [459, 842], [400, 842]]}, {"text": "viên", "tokens": [20098, 2078], "boundingBox": [[459, 802], [518, 802], [518, 842], [459, 842]]}, {"text": "CHIều", "tokens": [9610, 13765], "boundingBox": [[518, 802], [577, 802], [577, 842], [518, 842]]}, {"text": "3", "tokens": [1017], "boundingBox": [[577, 802], [636, 802], [636, 842], [577, 842]]}, {"text": "viên", "tokens": [20098, 2078], "boundingBox": [[636, 802], [695, 802], [695, 842], [636, 842]]}, {"text": "Tối", "tokens": [2000, 2072], "boundingBox": [[695, 802], [754, 802], [754, 842], [695, 842]]}, {"text": "3", "tokens": [1017], "boundingBox": [[754, 802], [813, 802], [813, 842], [754, 842]]}, {"text": "viên", "tokens": [20098, 2078], "boundingBox": [[813, 802], [872, 802], [872, 842], [813, 842]]}, {"text": "SL:", "tokens": [22889, 1024], "boundingBox": [[42, 807], [91, 807], [91, 835], [42, 835]]}, {"text": "90", "tokens": [3938], "boundingBox": [[91, 807], [140, 807], [140, 835], [91, 835]]}, {"text": "viên", "tokens": [20098, 2078], "boundingBox": [[140, 807], [189, 807], [189, 835], [140, 835]]}, {"text": "4)", "tokens": [1018, 1007], "boundingBox": [[37, 862], [144, 862], [144, 905], [37, 905]]}, {"text": "Loratadin", "tokens": [8840, 14660, 8718], "boundingBox": [[144, 862], [251, 862], [251, 905], [144, 905]]}, {"text": "(Sergurop)", "tokens": [1006, 14262, 27390, 7361, 1007], "boundingBox": [[251, 862], [358, 862], [358, 905], [251, 905]]}, {"text": "10mg", "tokens": [2184, 24798], "boundingBox": [[358, 862], [465, 862], [465, 905], [358, 905]]}, {"text": "Uống:", "tokens": [1057, 5063, 1024], "boundingBox": [[282, 930], [344, 930], [344, 970], [282, 970]]}, {"text": "TỐI", "tokens": [2000, 2072], "boundingBox": [[344, 930], [406, 930], [406, 970], [344, 970]]}, {"text": "1", "tokens": [1015], "boundingBox": [[406, 930], [468, 930], [468, 970], [406, 970]]}, {"text": "viên", "tokens": [20098, 2078], "boundingBox": [[468, 930], [530, 930], [530, 970], [468, 970]]}, {"text": "SL:", "tokens": [22889, 1024], "boundingBox": [[42, 935], [91, 935], [91, 962], [42, 962]]}, {"text": "10", "tokens": [2184], "boundingBox": [[91, 935], [140, 935], [140, 962], [91, 962]]}, {"text": "viên", "tokens": [20098, 2078], "boundingBox": [[140, 935], [189, 935], [189, 962], [140, 962]]}, {"text": "5)", "tokens": [1019, 1007], "boundingBox": [[37, 992], [154, 992], [154, 1032], [37, 1032]]}, {"text": "Methyl", "tokens": [25003], "boundingBox": [[154, 992], [271, 992], [271, 1032], [154, 1032]]}, {"text": "prednisolon", "tokens": [3653, 2094, 8977, 12898, 2078], "boundingBox": [[271, 992], [388, 992], [388, 1032], [271, 1032]]}, {"text": "(Methylprednisolon", "tokens": [1006, 25003, 28139, 2094, 8977, 12898, 2078], "boundingBox": [[388, 992], [505, 992], [505, 1032], [388, 1032]]}, {"text": "4)", "tokens": [1018, 1007], "boundingBox": [[505, 992], [622, 992], [622, 1032], [505, 1032]]}, {"text": "4mg", "tokens": [1018, 24798], "boundingBox": [[622, 992], [739, 992], [739, 1032], [622, 1032]]}, {"text": "Uống:", "tokens": [1057, 5063, 1024], "boundingBox": [[282, 1060], [349, 1060], [349, 1100], [282, 1100]]}, {"text": "Sáng", "tokens": [6369], "boundingBox": [[349, 1060], [416, 1060], [416, 1100], [349, 1100]]}, {"text": "4", "tokens": [1018], "boundingBox": [[416, 1060], [483, 1060], [483, 1100], [416, 1100]]}, {"text": "Viên", "tokens": [20098, 2078], "boundingBox": [[483, 1060], [550, 1060], [550, 1100], [483, 1100]]}, {"text": "SL:", "tokens": [22889, 1024], "boundingBox": [[42, 1062], [93, 1062], [93, 1092], [42, 1092]]}, {"text": "20", "tokens": [2322], "boundingBox": [[93, 1062], [144, 1062], [144, 1092], [93, 1092]]}, {"text": "Viên", "tokens": [20098, 2078], "boundingBox": [[144, 1062], [195, 1062], [195, 1092], [144, 1092]]}, {"text": "Lời", "tokens": [8840, 2072], "boundingBox": [[42, 1127], [99, 1127], [99, 1157], [42, 1157]]}, {"text": "dặn:", "tokens": [4907, 1024], "boundingBox": [[99, 1127], [156, 1127], [156, 1157], [99, 1157]]}, {"text": "Ngày", "tokens": [12835, 4710], "boundingBox": [[647, 1170], [710, 1170], [710, 1210], [647, 1210]]}, {"text": "28", "tokens": [2654], "boundingBox": [[710, 1170], [773, 1170], [773, 1210], [710, 1210]]}, {"text": "tháng", "tokens": [2084, 2290], "boundingBox": [[773, 1170], [836, 1170], [836, 1210], [773, 1210]]}, {"text": "12", "tokens": [2260], "boundingBox": [[836, 1170], [899, 1170], [899, 1210], [836, 1210]]}, {"text": "năm", "tokens": [15125], "boundingBox": [[899, 1170], [962, 1170], [962, 1210], [899, 1210]]}, {"text": "2021", "tokens": [25682], "boundingBox": [[962, 1170], [1025, 1170], [1025, 1210], [962, 1210]]}, {"text": "Bác", "tokens": [8670, 2278], "boundingBox": [[680, 1217], [744, 1217], [744, 1255], [680, 1255]]}, {"text": "sỹ/Y", "tokens": [25353, 1013, 1061], "boundingBox": [[744, 1217], [808, 1217], [808, 1255], [744, 1255]]}, {"text": "sỹ", "tokens": [25353], "boundingBox": [[808, 1217], [872, 1217], [872, 1255], [808, 1255]]}, {"text": "khám", "tokens": [1047, 3511], "boundingBox": [[872, 1217], [936, 1217], [936, 1255], [872, 1255]]}, {"text": "bệnh", "tokens": [3841, 2232], "boundingBox": [[936, 1217], [1000, 1217], [1000, 1255], [936, 1255]]}, {"text": "(Ký,", "tokens": [1006, 18712, 1010], "boundingBox": [[712, 1265], [763, 1265], [763, 1300], [712, 1300]]}, {"text": "ghi", "tokens": [1043, 4048], "boundingBox": [[763, 1265], [814, 1265], [814, 1300], [763, 1300]]}, {"text": "rõ", "tokens": [20996], "boundingBox": [[814, 1265], [865, 1265], [865, 1300], [814, 1300]]}, {"text": "họ", "tokens": [7570], "boundingBox": [[865, 1265], [916, 1265], [916, 1300], [865, 1300]]}, {"text": "tên)", "tokens": [2702, 1007], "boundingBox": [[916, 1265], [967, 1265], [967, 1300], [916, 1300]]}, {"text": "BSCKI.", "tokens": [23533, 3211, 1012], "boundingBox": [[669, 1403], [754, 1403], [754, 1442], [669, 1442]]}, {"text": "Trần", "tokens": [25283], "boundingBox": [[754, 1403], [839, 1403], [839, 1442], [754, 1442]]}, {"text": "Đức", "tokens": [1102, 14194], "boundingBox": [[839, 1403], [924, 1403], [924, 1442], [839, 1442]]}, {"text": "Thuận", "tokens": [16215, 13860], "boundingBox": [[924, 1403], [1009, 1403], [1009, 1442], [924, 1442]]}, {"text": "Khám", "tokens": [1047, 3511], "boundingBox": [[62, 1455], [125, 1455], [125, 1487], [62, 1487]]}, {"text": "lại", "tokens": [21110], "boundingBox": [[125, 1455], [188, 1455], [188, 1487], [125, 1487]]}, {"text": "xin", "tokens": [8418, 2078], "boundingBox": [[188, 1455], [251, 1455], [251, 1487], [188, 1487]]}, {"text": "mang", "tokens": [2158, 2290], "boundingBox": [[251, 1455], [314, 1455], [314, 1487], [251, 1487]]}, {"text": "theo", "tokens": [14833], "boundingBox": [[314, 1455], [377, 1455], [377, 1487], [314, 1487]]}, {"text": "đơn", "tokens": [1102, 2239], "boundingBox": [[377, 1455], [440, 1455], [440, 1487], [377, 1487]]}, {"text": "này", "tokens": [29349], "boundingBox": [[440, 1455], [503, 1455], [503, 1487], [440, 1487]]}, {"text": "Tên", "tokens": [2702], "boundingBox": [[62, 1495], [125, 1495], [125, 1542], [62, 1542]]}, {"text": "bố", "tokens": [8945], "boundingBox": [[125, 1495], [188, 1495], [188, 1542], [125, 1542]]}, {"text": "hoặc", "tokens": [7570, 6305], "boundingBox": [[188, 1495], [251, 1495], [251, 1542], [188, 1542]]}, {"text": "mẹ", "tokens": [2033], "boundingBox": [[251, 1495], [314, 1495], [314, 1542], [251, 1542]]}, {"text": "của", "tokens": [12731, 2050], "boundingBox": [[314, 1495], [377, 1495], [377, 1542], [314, 1542]]}, {"text": "trẻ", "tokens": [29461], "boundingBox": [[377, 1495], [440, 1495], [440, 1542], [377, 1542]]}, {"text": "hoặc", "tokens": [7570, 6305], "boundingBox": [[440, 1495], [503, 1495], [503, 1542], [440, 1542]]}, {"text": "người", "tokens": [12835, 19098, 2072], "boundingBox": [[503, 1495], [566, 1495], [566, 1542], [503, 1542]]}, {"text": "đưa", "tokens": [1102, 6692], "boundingBox": [[566, 1495], [629, 1495], [629, 1542], [566, 1542]]}, {"text": "trẻ", "tokens": [29461], "boundingBox": [[629, 1495], [692, 1495], [692, 1542], [629, 1542]]}, {"text": "đến", "tokens": [1102, 2368], "boundingBox": [[692, 1495], [755, 1495], [755, 1542], [692, 1542]]}, {"text": "khám", "tokens": [1047, 3511], "boundingBox": [[755, 1495], [818, 1495], [818, 1542], [755, 1542]]}, {"text": "bệnh,", "tokens": [3841, 2232, 1010], "boundingBox": [[818, 1495], [881, 1495], [881, 1542], [818, 1542]]}, {"text": "chữa", "tokens": [14684, 2050], "boundingBox": [[881, 1495], [944, 1495], [944, 1542], [881, 1542]]}, {"text": "bệnh", "tokens": [3841, 2232], "boundingBox": [[944, 1495], [1007, 1495], [1007, 1542], [944, 1542]]}], "parse": {"seq_len": 345, "input_ids": [101, 1102, 9013, 27793, 4886, 1024, 1102, 2239, 16215, 19098, 2278, 1038, 10536, 2102, 2064, 16660, 2290, 4705, 15125, 16371, 9212, 1102, 10441, 2078, 1024, 1048, 11387, 1011, 20098, 2213, 4830, 2522, 1102, 2401, 1025, 1006, 23290, 2509, 1012, 1014, 1007, 20098, 2213, 1102, 2050, 1047, 18471, 1047, 19991, 1102, 6305, 7632, 13765, 12436, 2072, 19817, 4886, 1025, 1006, 1044, 2620, 2487, 1007, 25223, 5414, 14684, 2278, 16660, 2290, 5495, 2078, 1102, 2378, 2232, 1025, 1006, 1048, 12376, 1007, 2089, 1102, 4710, 16215, 19098, 2278, 1102, 17301, 13012, 1024, 1015, 1007, 8292, 7011, 2571, 20303, 1006, 2034, 2571, 20303, 3156, 1007, 1014, 1010, 1019, 2290, 1057, 5063, 1024, 6369, 1016, 20098, 2078, 9610, 13765, 1016, 20098, 2078, 2000, 2072, 1016, 20098, 2078, 22889, 1024, 2382, 20098, 2078, 1016, 1007, 8840, 2595, 7361, 3217, 18940, 1006, 2033, 4143, 18940, 1007, 3438, 24798, 1057, 5063, 1024, 6369, 1015, 20098, 2078, 9610, 13765, 1015, 20098, 2078, 2000, 2072, 1015, 20098, 2078, 22889, 1024, 2382, 20098, 2078, 1017, 1007, 1102, 2378, 2232, 11374, 1010, 10384, 24209, 2050, 1006, 7570, 4017, 15876, 6672, 2102, 6829, 3070, 6583, 2080, 1007, 5018, 24798, 1009, 2322, 24798, 1057, 5063, 1024, 6369, 1017, 20098, 2078, 9610, 13765, 1017, 20098, 2078, 2000, 2072, 1017, 20098, 2078, 22889, 1024, 3938, 20098, 2078, 1018, 1007, 8840, 14660, 8718, 1006, 14262, 27390, 7361, 1007, 2184, 24798, 1057, 5063, 1024, 2000, 2072, 1015, 20098, 2078, 22889, 1024, 2184, 20098, 2078, 1019, 1007, 25003, 3653, 2094, 8977, 12898, 2078, 1006, 25003, 28139, 2094, 8977, 12898, 2078, 1018, 1007, 1018, 24798, 1057, 5063, 1024, 6369, 1018, 20098, 2078, 22889, 1024, 2322, 20098, 2078, 8840, 2072, 4907, 1024, 12835, 4710, 2654, 2084, 2290, 2260, 15125, 25682, 8670, 2278, 25353, 1013, 1061, 25353, 1047, 3511, 3841, 2232, 1006, 18712, 1010, 1043, 4048, 20996, 7570, 2702, 1007, 23533, 3211, 1012, 25283, 1102, 14194, 16215, 13860, 1047, 3511, 21110, 8418, 2078, 2158, 2290, 14833, 1102, 2239, 29349, 2702, 8945, 7570, 6305, 2033, 12731, 2050, 29461, 7570, 6305, 12835, 19098, 2072, 1102, 6692, 29461, 1102, 2368, 1047, 3511, 3841, 2232, 1010, 14684, 2050, 3841, 2232, 102, 0, 0, 0, 0, 0, 0, 0, 0, 0, 0, 0, 0, 0, 0, 0, 0, 0, 0, 0, 0, 0, 0, 0, 0, 0, 0, 0, 0, 0, 0, 0, 0, 0, 0, 0, 0, 0, 0, 0, 0, 0, 0, 0, 0, 0, 0, 0, 0, 0, 0, 0, 0, 0, 0, 0, 0, 0, 0, 0, 0, 0, 0, 0, 0, 0, 0, 0, 0, 0, 0, 0, 0, 0, 0, 0, 0, 0, 0, 0, 0, 0, 0, 0, 0, 0, 0, 0, 0, 0, 0, 0, 0, 0, 0, 0, 0, 0, 0, 0, 0, 0, 0, 0, 0, 0, 0, 0, 0, 0, 0, 0, 0, 0, 0, 0, 0, 0, 0, 0, 0, 0, 0, 0, 0, 0, 0, 0, 0, 0, 0, 0, 0, 0, 0, 0, 0, 0, 0, 0, 0, 0, 0, 0, 0, 0, 0, 0, 0, 0, 0, 0, 0, 0, 0, 0, 0, 0, 0, 0, 0, 0, 0, 0, 0, 0, 0, 0], "input_mask": [1, 1, 1, 1, 1, 1, 1, 1, 1, 1, 1, 1, 1, 1, 1, 1, 1, 1, 1, 1, 1, 1, 1, 1, 1, 1, 1, 1, 1, 1, 1, 1, 1, 1, 1, 1, 1, 1, 1, 1, 1, 1, 1, 1, 1, 1, 1, 1, 1, 1, 1, 1, 1, 1, 1, 1, 1, 1, 1, 1, 1, 1, 1, 1, 1, 1, 1, 1, 1, 1, 1, 1, 1, 1, 1, 1, 1, 1, 1, 1, 1, 1, 1, 1, 1, 1, 1, 1, 1, 1, 1, 1, 1, 1, 1, 1, 1, 1, 1, 1, 1, 1, 1, 1, 1, 1, 1, 1, 1, 1, 1, 1, 1, 1, 1, 1, 1, 1, 1, 1, 1, 1, 1, 1, 1, 1, 1, 1, 1, 1, 1, 1, 1, 1, 1, 1, 1, 1, 1, 1, 1, 1, 1, 1, 1, 1, 1, 1, 1, 1, 1, 1, 1, 1, 1, 1, 1, 1, 1, 1, 1, 1, 1, 1, 1, 1, 1, 1, 1, 1, 1, 1, 1, 1, 1, 1, 1, 1, 1, 1, 1, 1, 1, 1, 1, 1, 1, 1, 1, 1, 1, 1, 1, 1, 1, 1, 1, 1, 1, 1, 1, 1, 1, 1, 1, 1, 1, 1, 1, 1, 1, 1, 1, 1, 1, 1, 1, 1, 1, 1, 1, 1, 1, 1, 1, 1, 1, 1, 1, 1, 1, 1, 1, 1, 1, 1, 1, 1, 1, 1, 1, 1, 1, 1, 1, 1, 1, 1, 1, 1, 1, 1, 1, 1, 1, 1, 1, 1, 1, 1, 1, 1, 1, 1, 1, 1, 1, 1, 1, 1, 1, 1, 1, 1, 1, 1, 1, 1, 1, 1, 1, 1, 1, 1, 1, 1, 1, 1, 1, 1, 1, 1, 1, 1, 1, 1, 1, 1, 1, 1, 1, 1, 1, 1, 1, 1, 1, 1, 1, 1, 1, 1, 1, 1, 1, 1, 1, 1, 1, 1, 1, 1, 1, 1, 1, 1, 1, 1, 1, 1, 1, 1, 1, 1, 1, 1, 1, 1, 1, 1, 1, 1, 1, 1, 1, 0, 0, 0, 0, 0, 0, 0, 0, 0, 0, 0, 0, 0, 0, 0, 0, 0, 0, 0, 0, 0, 0, 0, 0, 0, 0, 0, 0, 0, 0, 0, 0, 0, 0, 0, 0, 0, 0, 0, 0, 0, 0, 0, 0, 0, 0, 0, 0, 0, 0, 0, 0, 0, 0, 0, 0, 0, 0, 0, 0, 0, 0, 0, 0, 0, 0, 0, 0, 0, 0, 0, 0, 0, 0, 0, 0, 0, 0, 0, 0, 0, 0, 0, 0, 0, 0, 0, 0, 0, 0, 0, 0, 0, 0, 0, 0, 0, 0, 0, 0, 0, 0, 0, 0, 0, 0, 0, 0, 0, 0, 0, 0, 0, 0, 0, 0, 0, 0, 0, 0, 0, 0, 0, 0, 0, 0, 0, 0, 0, 0, 0, 0, 0, 0, 0, 0, 0, 0, 0, 0, 0, 0, 0, 0, 0, 0, 0, 0, 0, 0, 0, 0, 0, 0, 0, 0, 0, 0, 0, 0, 0, 0, 0, 0, 0, 0, 0], "label_ids": [-100, 15, -100, 15, -100, -100, 15, -100, 15, -100, -100, 15, -100, -100, 15, 15, -100, 15, 15, 15, 1, 11, -100, -100, -100, 11, -100, 11, 11, -100, 11, 11, 11, -100, -100, 11, -100, -100, -100, -100, -100, 11, -100, 11, -100, 11, -100, 11, -100, 11, -100, 11, -100, 6, -100, 1, -100, -100, 11, -100, -100, -100, -100, 11, 11, 11, -100, 11, -100, 11, -100, 11, -100, -100, -100, 11, -100, -100, -100, 11, 6, -100, 15, -100, -100, 15, -100, 15, -100, 2, -100, 12, -100, -100, -100, 12, -100, -100, -100, 12, -100, 7, -100, -100, -100, 4, -100, -100, 14, 14, 14, -100, 14, -100, 14, 14, -100, 14, -100, 14, 9, -100, 3, -100, 13, 8, -100, 2, -100, 12, -100, -100, -100, -100, 12, -100, -100, -100, -100, 7, -100, 4, -100, -100, 14, 14, 14, -100, 14, -100, 14, 14, -100, 14, -100, 14, 9, -100, 3, -100, 13, 8, -100, 2, -100, 12, -100, -100, 12, -100, 12, 12, -100, 12, -100, -100, 12, -100, -100, 12, -100, 12, -100, -100, 7, -100, -100, -100, -100, 4, -100, -100, 14, 14, 14, -100, 14, -100, 14, 14, -100, 14, -100, 14, 9, -100, 3, -100, 13, 8, -100, 2, -100, 12, -100, -100, 12, -100, -100, -100, -100, 7, -100, 4, -100, -100, 14, -100, 14, 9, -100, 3, -100, 13, 8, -100, 2, -100, 12, 12, -100, -100, -100, -100, 12, -100, -100, -100, -100, -100, -100, 12, -100, 7, -100, 4, -100, -100, 14, 14, 9, -100, 3, -100, 13, 8, -100, 15, -100, 15, -100, 0, -100, 10, 10, -100, 10, 10, 5, 15, -100, 15, -100, -100, 15, 15, -100, 15, -100, 15, -100, -100, 15, -100, 15, 15, 15, -100, 15, -100, -100, 15, 15, -100, 15, -100, 15, -100, 15, 15, -100, 15, -100, 15, 15, -100, 15, 15, 15, 15, -100, 15, 15, -100, 15, 15, -100, 15, -100, -100, 15, -100, 15, 15, -100, 15, -100, 15, -100, -100, 15, -100, 15, -100, -100, -100, -100, -100, -100, -100, -100, -100, -100, -100, -100, -100, -100, -100, -100, -100, -100, -100, -100, -100, -100, -100, -100, -100, -100, -100, -100, -100, -100, -100, -100, -100, -100, -100, -100, -100, -100, -100, -100, -100, -100, -100, -100, -100, -100, -100, -100, -100, -100, -100, -100, -100, -100, -100, -100, -100, -100, -100, -100, -100, -100, -100, -100, -100, -100, -100, -100, -100, -100, -100, -100, -100, -100, -100, -100, -100, -100, -100, -100, -100, -100, -100, -100, -100, -100, -100, -100, -100, -100, -100, -100, -100, -100, -100, -100, -100, -100, -100, -100, -100, -100, -100, -100, -100, -100, -100, -100, -100, -100, -100, -100, -100, -100, -100, -100, -100, -100, -100, -100, -100, -100, -100, -100, -100, -100, -100, -100, -100, -100, -100, -100, -100, -100, -100, -100, -100, -100, -100, -100, -100, -100, -100, -100, -100, -100, -100, -100, -100, -100, -100, -100, -100, -100, -100, -100, -100, -100, -100, -100, -100, -100, -100, -100, -100, -100, -100, -100, -100]}}