{"form": [{"text": "TR\u1ea0M Y T\u1ebe X\u00c3 AN \u0110\u1ed2", "box": [37, 95, 302, 128], "label": "other", "words": [{"box": [37, 95, 81, 128], "text": "TR\u1ea0M"}, {"box": [81, 95, 125, 128], "text": "Y"}, {"box": [125, 95, 169, 128], "text": "T\u1ebe"}, {"box": [169, 95, 213, 128], "text": "X\u00c3"}, {"box": [213, 95, 257, 128], "text": "AN"}, {"box": [257, 95, 301, 128], "text": "\u0110\u1ed2"}]}, {"text": "S\u1ed1 phi\u1ebfu 1488/2021", "box": [554, 151, 795, 193], "label": "other", "words": [{"box": [554, 151, 634, 193], "text": "S\u1ed1"}, {"box": [634, 151, 714, 193], "text": "phi\u1ebfu"}, {"box": [714, 151, 794, 193], "text": "1488/2021"}]}, {"text": "4767158", "box": [935, 165, 1027, 190], "label": "other", "words": [{"box": [935, 165, 1027, 190], "text": "4767158"}]}, {"text": "TOA THU\u1ed0C BHYT", "box": [387, 195, 755, 242], "label": "other", "words": [{"box": [387, 195, 509, 242], "text": "TOA"}, {"box": [509, 195, 631, 242], "text": "THU\u1ed0C"}, {"box": [631, 195, 753, 242], "text": "BHYT"}]}, {"text": "Nam", "box": [927, 255, 977, 275], "label": "other", "words": [{"box": [927, 255, 977, 275], "text": "Nam"}]}, {"text": "N\u1eef", "box": [1025, 257, 1057, 277], "label": "other", "words": [{"box": [1025, 257, 1057, 277], "text": "N\u1eef"}]}, {"text": "2", "box": [370, 325, 390, 350], "label": "other", "words": [{"box": [370, 325, 390, 350], "text": "2"}]}, {"text": "35", "box": [447, 325, 480, 350], "label": "other", "words": [{"box": [447, 325, 480, 350], "text": "35"}]}, {"text": "35", "box": [545, 325, 577, 350], "label": "other", "words": [{"box": [545, 325, 577, 350], "text": "35"}]}, {"text": "206", "box": [650, 325, 695, 350], "label": "other", "words": [{"box": [650, 325, 695, 350], "text": "206"}]}, {"text": "35188", "box": [762, 325, 835, 350], "label": "other", "words": [{"box": [762, 325, 835, 350], "text": "35188"}]}, {"text": "MMHg Th\u00e2n nhi\u1ec7t: 38", "box": [674, 359, 932, 393], "label": "other", "words": [{"box": [674, 359, 738, 393], "text": "MMHg"}, {"box": [738, 359, 802, 393], "text": "Th\u00e2n"}, {"box": [802, 359, 866, 393], "text": "nhi\u1ec7t:"}, {"box": [866, 359, 930, 393], "text": "38"}]}, {"text": "L\u1ea7n/ph\u00fat Huy\u1ebft \u00e1p:", "box": [247, 362, 455, 390], "label": "other", "words": [{"box": [247, 362, 316, 390], "text": "L\u1ea7n/ph\u00fat"}, {"box": [316, 362, 385, 390], "text": "Huy\u1ebft"}, {"box": [385, 362, 454, 390], "text": "\u00e1p:"}]}, {"text": "M\u1ea1ch: 63", "box": [37, 365, 160, 390], "label": "other", "words": [{"box": [37, 365, 98, 390], "text": "M\u1ea1ch:"}, {"box": [98, 365, 159, 390], "text": "63"}]}, {"text": "100", "box": [500, 367, 615, 387], "label": "other", "words": [{"box": [500, 367, 615, 387], "text": "100"}]}, {"text": "C\u1eadn l\u00e2m s\u00e0ng:", "box": [36, 392, 185, 425], "label": "other", "words": [{"box": [36, 392, 85, 425], "text": "C\u1eadn"}, {"box": [85, 392, 134, 425], "text": "l\u00e2m"}, {"box": [134, 392, 183, 425], "text": "s\u00e0ng:"}]}, {"text": "Ch\u1ea5n \u0111o\u00e1n: J02 - Vi\u00eam h\u1ecdng c\u1ea5p; (G46?) H\u1ed9i ch\u1ee9ng m\u1ea1ch m\u00e1u n\u00e3o trong b\u1ec7nh m\u1ea1ch n\u00e3o (160-1677)", "box": [37, 420, 1057, 452], "label": "diagnose", "words": [{"box": [37, 420, 93, 452], "text": "Ch\u1ea5n"}, {"box": [93, 420, 149, 452], "text": "\u0111o\u00e1n:"}, {"box": [149, 420, 205, 452], "text": "J02"}, {"box": [205, 420, 261, 452], "text": "-"}, {"box": [261, 420, 317, 452], "text": "Vi\u00eam"}, {"box": [317, 420, 373, 452], "text": "h\u1ecdng"}, {"box": [373, 420, 429, 452], "text": "c\u1ea5p;"}, {"box": [429, 420, 485, 452], "text": "(G46?)"}, {"box": [485, 420, 541, 452], "text": "H\u1ed9i"}, {"box": [541, 420, 597, 452], "text": "ch\u1ee9ng"}, {"box": [597, 420, 653, 452], "text": "m\u1ea1ch"}, {"box": [653, 420, 709, 452], "text": "m\u00e1u"}, {"box": [709, 420, 765, 452], "text": "n\u00e3o"}, {"box": [765, 420, 821, 452], "text": "trong"}, {"box": [821, 420, 877, 452], "text": "b\u1ec7nh"}, {"box": [877, 420, 933, 452], "text": "m\u1ea1ch"}, {"box": [933, 420, 989, 452], "text": "n\u00e3o"}, {"box": [989, 420, 1045, 452], "text": "(160-1677)"}]}, {"text": "1) FABAMOX 500 500mg", "box": [64, 590, 455, 632], "label": "drugname", "words": [{"box": [64, 590, 161, 632], "text": "1)"}, {"box": [161, 590, 258, 632], "text": "FABAMOX"}, {"box": [258, 590, 355, 632], "text": "500"}, {"box": [355, 590, 452, 632], "text": "500mg"}]}, {"text": "SL: 20 Vi\u00ean", "box": [887, 592, 1057, 625], "label": "quantity", "words": [{"box": [887, 592, 943, 625], "text": "SL:"}, {"box": [943, 592, 999, 625], "text": "20"}, {"box": [999, 592, 1055, 625], "text": "Vi\u00ean"}]}, {"text": "Ghi ch\u00fa U\u1ed1ng:", "box": [49, 627, 235, 665], "label": "other", "words": [{"box": [49, 627, 111, 665], "text": "Ghi"}, {"box": [111, 627, 173, 665], "text": "ch\u00fa"}, {"box": [173, 627, 235, 665], "text": "U\u1ed1ng:"}]}, {"text": "Chi\u1ec1u 2 Vi\u00ean", "box": [767, 632, 905, 660], "label": "usage", "words": [{"box": [767, 632, 813, 660], "text": "Chi\u1ec1u"}, {"box": [813, 632, 859, 660], "text": "2"}, {"box": [859, 632, 905, 660], "text": "Vi\u00ean"}]}, {"text": "S\u00e1ng 2 Vi\u00ean", "box": [430, 635, 560, 665], "label": "usage", "words": [{"box": [430, 635, 473, 665], "text": "S\u00e1ng"}, {"box": [473, 635, 516, 665], "text": "2"}, {"box": [516, 635, 559, 665], "text": "Vi\u00ean"}]}, {"text": "2) PANACTOL 500mg", "box": [64, 669, 405, 710], "label": "drugname", "words": [{"box": [64, 669, 177, 710], "text": "2)"}, {"box": [177, 669, 290, 710], "text": "PANACTOL"}, {"box": [290, 669, 403, 710], "text": "500mg"}]}, {"text": "SL: 20 Vi\u00ean", "box": [887, 672, 1057, 705], "label": "quantity", "words": [{"box": [887, 672, 943, 705], "text": "SL:"}, {"box": [943, 672, 999, 705], "text": "20"}, {"box": [999, 672, 1055, 705], "text": "Vi\u00ean"}]}, {"text": "Ghi ch\u00fa U\u1ed1ng:", "box": [49, 705, 235, 743], "label": "other", "words": [{"box": [49, 705, 111, 743], "text": "Ghi"}, {"box": [111, 705, 173, 743], "text": "ch\u00fa"}, {"box": [173, 705, 235, 743], "text": "U\u1ed1ng:"}]}, {"text": "Chi\u1ec1u 2 Vi\u00ean", "box": [767, 710, 905, 737], "label": "usage", "words": [{"box": [767, 710, 813, 737], "text": "Chi\u1ec1u"}, {"box": [813, 710, 859, 737], "text": "2"}, {"box": [859, 710, 905, 737], "text": "Vi\u00ean"}]}, {"text": "S\u00e1ng 2 Vi\u00ean", "box": [430, 712, 560, 742], "label": "usage", "words": [{"box": [430, 712, 473, 742], "text": "S\u00e1ng"}, {"box": [473, 712, 516, 742], "text": "2"}, {"box": [516, 712, 559, 742], "text": "Vi\u00ean"}]}, {"text": "3) HO\u1ea0T HUY\u1ebeT D\u01af\u1ee0NG N\u00c3O 150mg+20mg", "box": [64, 742, 750, 788], "label": "drugname", "words": [{"box": [64, 742, 178, 788], "text": "3)"}, {"box": [178, 742, 292, 788], "text": "HO\u1ea0T"}, {"box": [292, 742, 406, 788], "text": "HUY\u1ebeT"}, {"box": [406, 742, 520, 788], "text": "D\u01af\u1ee0NG"}, {"box": [520, 742, 634, 788], "text": "N\u00c3O"}, {"box": [634, 742, 748, 788], "text": "150mg+20mg"}]}, {"text": "SL: 20 vi\u00ean", "box": [887, 749, 1049, 782], "label": "quantity", "words": [{"box": [887, 749, 941, 782], "text": "SL:"}, {"box": [941, 749, 995, 782], "text": "20"}, {"box": [995, 749, 1049, 782], "text": "vi\u00ean"}]}, {"text": "Ghi ch\u00fa u\u1ed1ng:", "box": [49, 786, 235, 820], "label": "other", "words": [{"box": [49, 786, 111, 820], "text": "Ghi"}, {"box": [111, 786, 173, 820], "text": "ch\u00fa"}, {"box": [173, 786, 235, 820], "text": "u\u1ed1ng:"}]}, {"text": "Chi\u1ec1u 2 vi\u00ean", "box": [765, 787, 897, 815], "label": "usage", "words": [{"box": [765, 787, 809, 815], "text": "Chi\u1ec1u"}, {"box": [809, 787, 853, 815], "text": "2"}, {"box": [853, 787, 897, 815], "text": "vi\u00ean"}]}, {"text": "S\u00e1ng 2 vi\u00ean", "box": [430, 792, 552, 820], "label": "usage", "words": [{"box": [430, 792, 470, 820], "text": "S\u00e1ng"}, {"box": [470, 792, 510, 820], "text": "2"}, {"box": [510, 792, 550, 820], "text": "vi\u00ean"}]}, {"text": "C\u1ed9ng kho\u1ea3n: 3 kho\u1ea3n", "box": [45, 835, 290, 862], "label": "other", "words": [{"box": [45, 835, 106, 862], "text": "C\u1ed9ng"}, {"box": [106, 835, 167, 862], "text": "kho\u1ea3n:"}, {"box": [167, 835, 228, 862], "text": "3"}, {"box": [228, 835, 289, 862], "text": "kho\u1ea3n"}]}, {"text": "L\u1eddi d\u1eb7n \u0111\u01a1n thu\u1ed1c:", "box": [44, 866, 242, 898], "label": "other", "words": [{"box": [44, 866, 93, 898], "text": "L\u1eddi"}, {"box": [93, 866, 142, 898], "text": "d\u1eb7n"}, {"box": [142, 866, 191, 898], "text": "\u0111\u01a1n"}, {"box": [191, 866, 240, 898], "text": "thu\u1ed1c:"}]}, {"text": "Ng\u00e0y h\u1eb9n t\u00e1i kh\u00e1m:", "box": [45, 910, 247, 937], "label": "other", "words": [{"box": [45, 910, 95, 937], "text": "Ng\u00e0y"}, {"box": [95, 910, 145, 937], "text": "h\u1eb9n"}, {"box": [145, 910, 195, 937], "text": "t\u00e1i"}, {"box": [195, 910, 245, 937], "text": "kh\u00e1m:"}]}, {"text": "Ng\u00e0y 16/11/2021", "box": [722, 962, 925, 990], "label": "date", "words": [{"box": [722, 962, 823, 990], "text": "Ng\u00e0y"}, {"box": [823, 962, 924, 990], "text": "16/11/2021"}]}, {"text": "B\u1ec7nh nh\u00e2n k\u00fd nh\u1eadn", "box": [92, 990, 292, 1017], "label": "other", "words": [{"box": [92, 990, 142, 1017], "text": "B\u1ec7nh"}, {"box": [142, 990, 192, 1017], "text": "nh\u00e2n"}, {"box": [192, 990, 242, 1017], "text": "k\u00fd"}, {"box": [242, 990, 292, 1017], "text": "nh\u1eadn"}]}, {"text": "Y, B\u00e1c s\u0129 \u0111i\u1ec1u tr\u1ecb", "box": [737, 1000, 912, 1030], "label": "other", "words": [{"box": [737, 1000, 772, 1030], "text": "Y,"}, {"box": [772, 1000, 807, 1030], "text": "B\u00e1c"}, {"box": [807, 1000, 842, 1030], "text": "s\u0129"}, {"box": [842, 1000, 877, 1030], "text": "\u0111i\u1ec1u"}, {"box": [877, 1000, 912, 1030], "text": "tr\u1ecb"}]}, {"text": "BS. \u0110\u00e0o Xu\u00e2n Tu\u00e2n", "box": [700, 1115, 930, 1140], "label": "other", "words": [{"box": [700, 1115, 757, 1140], "text": "BS."}, {"box": [757, 1115, 814, 1140], "text": "\u0110\u00e0o"}, {"box": [814, 1115, 871, 1140], "text": "Xu\u00e2n"}, {"box": [871, 1115, 928, 1140], "text": "Tu\u00e2n"}]}, {"text": "T\u00e1i kh\u00e1m xin mang theo \u0111\u01a1n, x\u00e9t nghi\u1ec7m, phim (n\u1ebfu c\u00f3)", "box": [44, 1194, 617, 1227], "label": "other", "words": [{"box": [44, 1194, 96, 1227], "text": "T\u00e1i"}, {"box": [96, 1194, 148, 1227], "text": "kh\u00e1m"}, {"box": [148, 1194, 200, 1227], "text": "xin"}, {"box": [200, 1194, 252, 1227], "text": "mang"}, {"box": [252, 1194, 304, 1227], "text": "theo"}, {"box": [304, 1194, 356, 1227], "text": "\u0111\u01a1n,"}, {"box": [356, 1194, 408, 1227], "text": "x\u00e9t"}, {"box": [408, 1194, 460, 1227], "text": "nghi\u1ec7m,"}, {"box": [460, 1194, 512, 1227], "text": "phim"}, {"box": [512, 1194, 564, 1227], "text": "(n\u1ebfu"}, {"box": [564, 1194, 616, 1227], "text": "c\u00f3)"}]}, {"text": "04/01/2022 20:35:07", "box": [877, 1255, 1089, 1280], "label": "other", "words": [{"box": [877, 1255, 983, 1280], "text": "04/01/2022"}, {"box": [983, 1255, 1089, 1280], "text": "20:35:07"}]}]}