{"form": [{"text": "Khoa Kh\u00e1m b\u1ec7nh", "box": [37, 102, 217, 129], "label": "other", "words": [{"box": [37, 102, 97, 129], "text": "Khoa"}, {"box": [97, 102, 157, 129], "text": "Kh\u00e1m"}, {"box": [157, 102, 217, 129], "text": "b\u1ec7nh"}]}, {"text": "B\u1ed1c kh\u00e1m Ti\u1ec3u \u0111\u01b0\u1eddng 2", "box": [36, 146, 285, 183], "label": "other", "words": [{"box": [36, 146, 85, 183], "text": "B\u1ed1c"}, {"box": [85, 146, 134, 183], "text": "kh\u00e1m"}, {"box": [134, 146, 183, 183], "text": "Ti\u1ec3u"}, {"box": [183, 146, 232, 183], "text": "\u0111\u01b0\u1eddng"}, {"box": [232, 146, 281, 183], "text": "2"}]}, {"text": "S\u1ed1 phi\u1ebfu 37666/2021", "box": [554, 151, 813, 193], "label": "other", "words": [{"box": [554, 151, 640, 193], "text": "S\u1ed1"}, {"box": [640, 151, 726, 193], "text": "phi\u1ebfu"}, {"box": [726, 151, 812, 193], "text": "37666/2021"}]}, {"text": "4747340", "box": [935, 165, 1027, 190], "label": "other", "words": [{"box": [935, 165, 1027, 190], "text": "4747340"}]}, {"text": "TOA THU\u1ed0C BHYT", "box": [387, 195, 757, 242], "label": "other", "words": [{"box": [387, 195, 510, 242], "text": "TOA"}, {"box": [510, 195, 633, 242], "text": "THU\u1ed0C"}, {"box": [633, 195, 756, 242], "text": "BHYT"}]}, {"text": "Nam", "box": [925, 252, 977, 275], "label": "other", "words": [{"box": [925, 252, 977, 275], "text": "Nam"}]}, {"text": "N\u1eef", "box": [1022, 255, 1057, 277], "label": "other", "words": [{"box": [1022, 255, 1057, 277], "text": "N\u1eef"}]}, {"text": "20257", "box": [762, 322, 835, 350], "label": "other", "words": [{"box": [762, 322, 835, 350], "text": "20257"}]}, {"text": "35", "box": [447, 325, 480, 350], "label": "other", "words": [{"box": [447, 325, 480, 350], "text": "35"}]}, {"text": "35", "box": [545, 325, 577, 350], "label": "other", "words": [{"box": [545, 325, 577, 350], "text": "35"}]}, {"text": "206", "box": [650, 325, 695, 350], "label": "other", "words": [{"box": [650, 325, 695, 350], "text": "206"}]}, {"text": "4", "box": [372, 327, 390, 347], "label": "other", "words": [{"box": [372, 327, 390, 347], "text": "4"}]}, {"text": "mmHg Th\u00e2n nhi\u1ec7t: 37", "box": [674, 361, 930, 393], "label": "other", "words": [{"box": [674, 361, 738, 393], "text": "mmHg"}, {"box": [738, 361, 802, 393], "text": "Th\u00e2n"}, {"box": [802, 361, 866, 393], "text": "nhi\u1ec7t:"}, {"box": [866, 361, 930, 393], "text": "37"}]}, {"text": "l\u1ea7n/ph\u00fat Huy\u1ebft \u00e1p:", "box": [250, 362, 455, 390], "label": "other", "words": [{"box": [250, 362, 318, 390], "text": "l\u1ea7n/ph\u00fat"}, {"box": [318, 362, 386, 390], "text": "Huy\u1ebft"}, {"box": [386, 362, 454, 390], "text": "\u00e1p:"}]}, {"text": "M\u1ea1ch:", "box": [37, 365, 105, 390], "label": "other", "words": [{"box": [37, 365, 105, 390], "text": "M\u1ea1ch:"}]}, {"text": "130", "box": [495, 365, 615, 387], "label": "other", "words": [{"box": [495, 365, 615, 387], "text": "130"}]}, {"text": "80", "box": [135, 367, 160, 387], "label": "other", "words": [{"box": [135, 367, 160, 387], "text": "80"}]}, {"text": "C\u1eadn l\u00e2m s\u00e0ng:", "box": [36, 392, 185, 425], "label": "other", "words": [{"box": [36, 392, 85, 425], "text": "C\u1eadn"}, {"box": [85, 392, 134, 425], "text": "l\u00e2m"}, {"box": [134, 392, 183, 425], "text": "s\u00e0ng:"}]}, {"text": "Ch\u1ea7n \u0111o\u00e1n: Ell - B\u1ec7nh \u0111\u00e1i th\u00e1o \u0111\u01b0\u1eddng kh\u00f4ng ph\u1ee5 thu\u1ed9c insuline;; (110) B\u1ec7nh l\u00fd t\u0103ng huy\u1ebft \u00e1p; (N18)", "box": [37, 422, 1064, 452], "label": "diagnose", "words": [{"box": [37, 422, 91, 452], "text": "Ch\u1ea7n"}, {"box": [91, 422, 145, 452], "text": "\u0111o\u00e1n:"}, {"box": [145, 422, 199, 452], "text": "Ell"}, {"box": [199, 422, 253, 452], "text": "-"}, {"box": [253, 422, 307, 452], "text": "B\u1ec7nh"}, {"box": [307, 422, 361, 452], "text": "\u0111\u00e1i"}, {"box": [361, 422, 415, 452], "text": "th\u00e1o"}, {"box": [415, 422, 469, 452], "text": "\u0111\u01b0\u1eddng"}, {"box": [469, 422, 523, 452], "text": "kh\u00f4ng"}, {"box": [523, 422, 577, 452], "text": "ph\u1ee5"}, {"box": [577, 422, 631, 452], "text": "thu\u1ed9c"}, {"box": [631, 422, 685, 452], "text": "insuline;;"}, {"box": [685, 422, 739, 452], "text": "(110)"}, {"box": [739, 422, 793, 452], "text": "B\u1ec7nh"}, {"box": [793, 422, 847, 452], "text": "l\u00fd"}, {"box": [847, 422, 901, 452], "text": "t\u0103ng"}, {"box": [901, 422, 955, 452], "text": "huy\u1ebft"}, {"box": [955, 422, 1009, 452], "text": "\u00e1p;"}, {"box": [1009, 422, 1063, 452], "text": "(N18)"}]}, {"text": "Suy th\u1eadn m\u00e3n t\u00ednh", "box": [37, 455, 225, 480], "label": "diagnose", "words": [{"box": [37, 455, 84, 480], "text": "Suy"}, {"box": [84, 455, 131, 480], "text": "th\u1eadn"}, {"box": [131, 455, 178, 480], "text": "m\u00e3n"}, {"box": [178, 455, 225, 480], "text": "t\u00ednh"}]}, {"text": "1) PAMLONOR 5mg", "box": [64, 590, 382, 632], "label": "drugname", "words": [{"box": [64, 590, 170, 632], "text": "1)"}, {"box": [170, 590, 276, 632], "text": "PAMLONOR"}, {"box": [276, 590, 382, 632], "text": "5mg"}]}, {"text": "SL: 60 Vi\u00ean", "box": [887, 591, 1057, 627], "label": "quantity", "words": [{"box": [887, 591, 943, 627], "text": "SL:"}, {"box": [943, 591, 999, 627], "text": "60"}, {"box": [999, 591, 1055, 627], "text": "Vi\u00ean"}]}, {"text": "Ghi ch\u00fa U\u1ed1ng:", "box": [49, 627, 235, 665], "label": "other", "words": [{"box": [49, 627, 111, 665], "text": "Ghi"}, {"box": [111, 627, 173, 665], "text": "ch\u00fa"}, {"box": [173, 627, 235, 665], "text": "U\u1ed1ng:"}]}, {"text": "S\u00e1ng 1 Vi\u00ean", "box": [430, 635, 560, 665], "label": "usage", "words": [{"box": [430, 635, 473, 665], "text": "S\u00e1ng"}, {"box": [473, 635, 516, 665], "text": "1"}, {"box": [516, 635, 559, 665], "text": "Vi\u00ean"}]}, {"text": "C\u1ed9ng kho\u1ea3n: 1 kho\u1ea3n", "box": [45, 677, 290, 705], "label": "other", "words": [{"box": [45, 677, 106, 705], "text": "C\u1ed9ng"}, {"box": [106, 677, 167, 705], "text": "kho\u1ea3n:"}, {"box": [167, 677, 228, 705], "text": "1"}, {"box": [228, 677, 289, 705], "text": "kho\u1ea3n"}]}, {"text": "L\u1eddi d\u1eb7n \u0111\u01a1n thu\u1ed1c: KH\u00e1m L\u1ea1i 1/10/2021", "box": [45, 712, 492, 740], "label": "other", "words": [{"box": [45, 712, 108, 740], "text": "L\u1eddi"}, {"box": [108, 712, 171, 740], "text": "d\u1eb7n"}, {"box": [171, 712, 234, 740], "text": "\u0111\u01a1n"}, {"box": [234, 712, 297, 740], "text": "thu\u1ed1c:"}, {"box": [297, 712, 360, 740], "text": "KH\u00e1m"}, {"box": [360, 712, 423, 740], "text": "L\u1ea1i"}, {"box": [423, 712, 486, 740], "text": "1/10/2021"}]}, {"text": "Ng\u00e0y h\u1eb9n t\u00e1i kh\u00e1m:", "box": [44, 752, 247, 785], "label": "other", "words": [{"box": [44, 752, 94, 785], "text": "Ng\u00e0y"}, {"box": [94, 752, 144, 785], "text": "h\u1eb9n"}, {"box": [144, 752, 194, 785], "text": "t\u00e1i"}, {"box": [194, 752, 244, 785], "text": "kh\u00e1m:"}]}, {"text": "Ng\u00e0y 02/08/2021", "box": [722, 807, 925, 835], "label": "date", "words": [{"box": [722, 807, 823, 835], "text": "Ng\u00e0y"}, {"box": [823, 807, 924, 835], "text": "02/08/2021"}]}, {"text": "B\u1ec7nh nh\u00e2n k\u00fd nh\u1eadn", "box": [92, 832, 292, 860], "label": "other", "words": [{"box": [92, 832, 142, 860], "text": "B\u1ec7nh"}, {"box": [142, 832, 192, 860], "text": "nh\u00e2n"}, {"box": [192, 832, 242, 860], "text": "k\u00fd"}, {"box": [242, 832, 292, 860], "text": "nh\u1eadn"}]}, {"text": "Y, B\u00e1c s\u0129 \u0111i\u1ec1u tr\u1ecb", "box": [737, 845, 912, 872], "label": "other", "words": [{"box": [737, 845, 772, 872], "text": "Y,"}, {"box": [772, 845, 807, 872], "text": "B\u00e1c"}, {"box": [807, 845, 842, 872], "text": "s\u0129"}, {"box": [842, 845, 877, 872], "text": "\u0111i\u1ec1u"}, {"box": [877, 845, 912, 872], "text": "tr\u1ecb"}]}, {"text": "BS. Nguy\u1ec5n \u0110\u1ee9c Th\u00e1i", "box": [687, 951, 943, 992], "label": "other", "words": [{"box": [687, 951, 751, 992], "text": "BS."}, {"box": [751, 951, 815, 992], "text": "Nguy\u1ec5n"}, {"box": [815, 951, 879, 992], "text": "\u0110\u1ee9c"}, {"box": [879, 951, 943, 992], "text": "Th\u00e1i"}]}, {"text": "T\u00e1i kh\u00e1m xin mang theo \u0111\u01a1n, x\u00e9t nghi\u1ec7m, phim (n\u1ebfu c\u00f3)", "box": [44, 1037, 617, 1071], "label": "other", "words": [{"box": [44, 1037, 96, 1071], "text": "T\u00e1i"}, {"box": [96, 1037, 148, 1071], "text": "kh\u00e1m"}, {"box": [148, 1037, 200, 1071], "text": "xin"}, {"box": [200, 1037, 252, 1071], "text": "mang"}, {"box": [252, 1037, 304, 1071], "text": "theo"}, {"box": [304, 1037, 356, 1071], "text": "\u0111\u01a1n,"}, {"box": [356, 1037, 408, 1071], "text": "x\u00e9t"}, {"box": [408, 1037, 460, 1071], "text": "nghi\u1ec7m,"}, {"box": [460, 1037, 512, 1071], "text": "phim"}, {"box": [512, 1037, 564, 1071], "text": "(n\u1ebfu"}, {"box": [564, 1037, 616, 1071], "text": "c\u00f3)"}]}, {"text": "04/01/2022 23:37:11", "box": [877, 1100, 1087, 1125], "label": "other", "words": [{"box": [877, 1100, 982, 1125], "text": "04/01/2022"}, {"box": [982, 1100, 1087, 1125], "text": "23:37:11"}]}]}