{"form": [{"text": "Khoa Kh\u00e1m b\u1ec7nh", "box": [37, 102, 217, 129], "label": "other", "words": [{"box": [37, 102, 97, 129], "text": "Khoa"}, {"box": [97, 102, 157, 129], "text": "Kh\u00e1m"}, {"box": [157, 102, 217, 129], "text": "b\u1ec7nh"}]}, {"text": "B\u1ed1c kh\u00e1m n\u1ed9i", "box": [37, 146, 188, 180], "label": "other", "words": [{"box": [37, 146, 87, 180], "text": "B\u1ed1c"}, {"box": [87, 146, 137, 180], "text": "kh\u00e1m"}, {"box": [137, 146, 187, 180], "text": "n\u1ed9i"}]}, {"text": "S\u1ed1 phi\u1ebfu 36684/2021", "box": [554, 151, 813, 193], "label": "other", "words": [{"box": [554, 151, 640, 193], "text": "S\u1ed1"}, {"box": [640, 151, 726, 193], "text": "phi\u1ebfu"}, {"box": [726, 151, 812, 193], "text": "36684/2021"}]}, {"text": "4688368", "box": [935, 165, 1027, 190], "label": "other", "words": [{"box": [935, 165, 1027, 190], "text": "4688368"}]}, {"text": "TOA THU\u1ed0C BHYT", "box": [387, 195, 757, 242], "label": "other", "words": [{"box": [387, 195, 510, 242], "text": "TOA"}, {"box": [510, 195, 633, 242], "text": "THU\u1ed0C"}, {"box": [633, 195, 756, 242], "text": "BHYT"}]}, {"text": "Nam", "box": [925, 252, 977, 277], "label": "other", "words": [{"box": [925, 252, 977, 277], "text": "Nam"}]}, {"text": "N\u1eef", "box": [1022, 252, 1057, 277], "label": "other", "words": [{"box": [1022, 252, 1057, 277], "text": "N\u1eef"}]}, {"text": "26366", "box": [762, 322, 835, 350], "label": "other", "words": [{"box": [762, 322, 835, 350], "text": "26366"}]}, {"text": "3", "box": [370, 325, 387, 350], "label": "other", "words": [{"box": [370, 325, 387, 350], "text": "3"}]}, {"text": "35", "box": [447, 325, 480, 350], "label": "other", "words": [{"box": [447, 325, 480, 350], "text": "35"}]}, {"text": "35", "box": [545, 325, 577, 350], "label": "other", "words": [{"box": [545, 325, 577, 350], "text": "35"}]}, {"text": "206", "box": [650, 325, 695, 350], "label": "other", "words": [{"box": [650, 325, 695, 350], "text": "206"}]}, {"text": "l\u1ea7n/ph\u00fat Huy\u1ebft \u00e1p:", "box": [247, 360, 455, 390], "label": "other", "words": [{"box": [247, 360, 316, 390], "text": "l\u1ea7n/ph\u00fat"}, {"box": [316, 360, 385, 390], "text": "Huy\u1ebft"}, {"box": [385, 360, 454, 390], "text": "\u00e1p:"}]}, {"text": "mmHg Th\u00e2n nhi\u1ec7t: 36.7", "box": [674, 360, 950, 393], "label": "other", "words": [{"box": [674, 360, 743, 393], "text": "mmHg"}, {"box": [743, 360, 812, 393], "text": "Th\u00e2n"}, {"box": [812, 360, 881, 393], "text": "nhi\u1ec7t:"}, {"box": [881, 360, 950, 393], "text": "36.7"}]}, {"text": "M\u1ea1ch:", "box": [37, 365, 105, 390], "label": "other", "words": [{"box": [37, 365, 105, 390], "text": "M\u1ea1ch:"}]}, {"text": "80", "box": [132, 365, 160, 387], "label": "other", "words": [{"box": [132, 365, 160, 387], "text": "80"}]}, {"text": "120", "box": [500, 367, 612, 387], "label": "other", "words": [{"box": [500, 367, 612, 387], "text": "120"}]}, {"text": "C\u1eadn l\u00e2m s\u00e0ng: T\u1ed5ng ph\u00e2n t\u00edch t\u1ebf b\u00e0o m\u00e1u ngo\u1ea1i vi (b\u1eb1ng m\u00e1y \u0111\u1ebfm laser), T\u1ed5ng ph\u00e2n t\u00edch n\u01b0\u1edbc ti\u1ec3u", "box": [37, 392, 1037, 425], "label": "other", "words": [{"box": [37, 392, 87, 425], "text": "C\u1eadn"}, {"box": [87, 392, 137, 425], "text": "l\u00e2m"}, {"box": [137, 392, 187, 425], "text": "s\u00e0ng:"}, {"box": [187, 392, 237, 425], "text": "T\u1ed5ng"}, {"box": [237, 392, 287, 425], "text": "ph\u00e2n"}, {"box": [287, 392, 337, 425], "text": "t\u00edch"}, {"box": [337, 392, 387, 425], "text": "t\u1ebf"}, {"box": [387, 392, 437, 425], "text": "b\u00e0o"}, {"box": [437, 392, 487, 425], "text": "m\u00e1u"}, {"box": [487, 392, 537, 425], "text": "ngo\u1ea1i"}, {"box": [537, 392, 587, 425], "text": "vi"}, {"box": [587, 392, 637, 425], "text": "(b\u1eb1ng"}, {"box": [637, 392, 687, 425], "text": "m\u00e1y"}, {"box": [687, 392, 737, 425], "text": "\u0111\u1ebfm"}, {"box": [737, 392, 787, 425], "text": "laser),"}, {"box": [787, 392, 837, 425], "text": "T\u1ed5ng"}, {"box": [837, 392, 887, 425], "text": "ph\u00e2n"}, {"box": [887, 392, 937, 425], "text": "t\u00edch"}, {"box": [937, 392, 987, 425], "text": "n\u01b0\u1edbc"}, {"box": [987, 392, 1037, 425], "text": "ti\u1ec3u"}]}, {"text": "(B\u1eb1ng m\u00e1y t\u1ef1 \u0111\u1ed9ng), \u0110\u1ecbnh l\u01b0\u1ee3ng Acid Uric (M\u00e1u), \u0110\u1ecbnh l\u01b0\u1ee3ng Cholesterol to\u00e0n ph\u1ea7n (m\u00e1u), \u0110\u1ecbnh l\u01b0\u1ee3ng", "box": [37, 422, 1095, 452], "label": "other", "words": [{"box": [37, 422, 99, 452], "text": "(B\u1eb1ng"}, {"box": [99, 422, 161, 452], "text": "m\u00e1y"}, {"box": [161, 422, 223, 452], "text": "t\u1ef1"}, {"box": [223, 422, 285, 452], "text": "\u0111\u1ed9ng),"}, {"box": [285, 422, 347, 452], "text": "\u0110\u1ecbnh"}, {"box": [347, 422, 409, 452], "text": "l\u01b0\u1ee3ng"}, {"box": [409, 422, 471, 452], "text": "Acid"}, {"box": [471, 422, 533, 452], "text": "Uric"}, {"box": [533, 422, 595, 452], "text": "(M\u00e1u),"}, {"box": [595, 422, 657, 452], "text": "\u0110\u1ecbnh"}, {"box": [657, 422, 719, 452], "text": "l\u01b0\u1ee3ng"}, {"box": [719, 422, 781, 452], "text": "Cholesterol"}, {"box": [781, 422, 843, 452], "text": "to\u00e0n"}, {"box": [843, 422, 905, 452], "text": "ph\u1ea7n"}, {"box": [905, 422, 967, 452], "text": "(m\u00e1u),"}, {"box": [967, 422, 1029, 452], "text": "\u0110\u1ecbnh"}, {"box": [1029, 422, 1091, 452], "text": "l\u01b0\u1ee3ng"}]}, {"text": "Glucose [M\u00e1u], \u0110\u1ecbnh l\u01b0\u1ee3ng HDL-C (High density lipoprotein Cholesterol) [M\u00e1u], \u0110\u1ecbnh l\u01b0\u1ee3ng", "box": [37, 455, 992, 482], "label": "other", "words": [{"box": [37, 455, 116, 482], "text": "Glucose"}, {"box": [116, 455, 195, 482], "text": "[M\u00e1u],"}, {"box": [195, 455, 274, 482], "text": "\u0110\u1ecbnh"}, {"box": [274, 455, 353, 482], "text": "l\u01b0\u1ee3ng"}, {"box": [353, 455, 432, 482], "text": "HDL-C"}, {"box": [432, 455, 511, 482], "text": "(High"}, {"box": [511, 455, 590, 482], "text": "density"}, {"box": [590, 455, 669, 482], "text": "lipoprotein"}, {"box": [669, 455, 748, 482], "text": "Cholesterol)"}, {"box": [748, 455, 827, 482], "text": "[M\u00e1u],"}, {"box": [827, 455, 906, 482], "text": "\u0110\u1ecbnh"}, {"box": [906, 455, 985, 482], "text": "l\u01b0\u1ee3ng"}]}, {"text": "Triglycerid (m\u00e1u) [M\u00e1u], \u0110o ho\u1ea1t \u0111\u1ed9 ALT (GPT) [M\u00e1u], \u0110o ho\u1ea1t \u0111\u1ed9 AST (GOT) [M\u00e1u], \u0110\u1ecbnh l\u01b0\u1ee3ng", "box": [37, 480, 1057, 512], "label": "other", "words": [{"box": [37, 480, 97, 512], "text": "Triglycerid"}, {"box": [97, 480, 157, 512], "text": "(m\u00e1u)"}, {"box": [157, 480, 217, 512], "text": "[M\u00e1u],"}, {"box": [217, 480, 277, 512], "text": "\u0110o"}, {"box": [277, 480, 337, 512], "text": "ho\u1ea1t"}, {"box": [337, 480, 397, 512], "text": "\u0111\u1ed9"}, {"box": [397, 480, 457, 512], "text": "ALT"}, {"box": [457, 480, 517, 512], "text": "(GPT)"}, {"box": [517, 480, 577, 512], "text": "[M\u00e1u],"}, {"box": [577, 480, 637, 512], "text": "\u0110o"}, {"box": [637, 480, 697, 512], "text": "ho\u1ea1t"}, {"box": [697, 480, 757, 512], "text": "\u0111\u1ed9"}, {"box": [757, 480, 817, 512], "text": "AST"}, {"box": [817, 480, 877, 512], "text": "(GOT)"}, {"box": [877, 480, 937, 512], "text": "[M\u00e1u],"}, {"box": [937, 480, 997, 512], "text": "\u0110\u1ecbnh"}, {"box": [997, 480, 1057, 512], "text": "l\u01b0\u1ee3ng"}]}, {"text": "Creatinin (m\u00e1u), \u0110i\u1ec7n gi\u1ea3i \u0111\u1ed3 (Na, K, Cl) [M\u00e1u]; \u0110i\u1ec7n tim th\u01b0\u1eddng", "box": [37, 507, 705, 540], "label": "other", "words": [{"box": [37, 507, 92, 540], "text": "Creatinin"}, {"box": [92, 507, 147, 540], "text": "(m\u00e1u),"}, {"box": [147, 507, 202, 540], "text": "\u0110i\u1ec7n"}, {"box": [202, 507, 257, 540], "text": "gi\u1ea3i"}, {"box": [257, 507, 312, 540], "text": "\u0111\u1ed3"}, {"box": [312, 507, 367, 540], "text": "(Na,"}, {"box": [367, 507, 422, 540], "text": "K,"}, {"box": [422, 507, 477, 540], "text": "Cl)"}, {"box": [477, 507, 532, 540], "text": "[M\u00e1u];"}, {"box": [532, 507, 587, 540], "text": "\u0110i\u1ec7n"}, {"box": [587, 507, 642, 540], "text": "tim"}, {"box": [642, 507, 697, 540], "text": "th\u01b0\u1eddng"}]}, {"text": "Ch\u1ea5n \u0111o\u00e1n: 110 - B\u1ec7nh l\u00fd t\u0103ng huy\u1ebft \u00e1p; (E78.1) T\u0103ng triglycerid m\u00e1u \u0111\u01a1n thu\u1ea7n", "box": [37, 535, 857, 567], "label": "diagnose", "words": [{"box": [37, 535, 91, 567], "text": "Ch\u1ea5n"}, {"box": [91, 535, 145, 567], "text": "\u0111o\u00e1n:"}, {"box": [145, 535, 199, 567], "text": "110"}, {"box": [199, 535, 253, 567], "text": "-"}, {"box": [253, 535, 307, 567], "text": "B\u1ec7nh"}, {"box": [307, 535, 361, 567], "text": "l\u00fd"}, {"box": [361, 535, 415, 567], "text": "t\u0103ng"}, {"box": [415, 535, 469, 567], "text": "huy\u1ebft"}, {"box": [469, 535, 523, 567], "text": "\u00e1p;"}, {"box": [523, 535, 577, 567], "text": "(E78.1)"}, {"box": [577, 535, 631, 567], "text": "T\u0103ng"}, {"box": [631, 535, 685, 567], "text": "triglycerid"}, {"box": [685, 535, 739, 567], "text": "m\u00e1u"}, {"box": [739, 535, 793, 567], "text": "\u0111\u01a1n"}, {"box": [793, 535, 847, 567], "text": "thu\u1ea7n"}]}, {"text": "SL: 30 vi\u00ean", "box": [887, 707, 1049, 739], "label": "quantity", "words": [{"box": [887, 707, 941, 739], "text": "SL:"}, {"box": [941, 707, 995, 739], "text": "30"}, {"box": [995, 707, 1049, 739], "text": "vi\u00ean"}]}, {"text": "1) HANGITOR PLUS 40mg+12,5mg", "box": [65, 707, 597, 747], "label": "drugname", "words": [{"box": [65, 707, 198, 747], "text": "1)"}, {"box": [198, 707, 331, 747], "text": "HANGITOR"}, {"box": [331, 707, 464, 747], "text": "PLUS"}, {"box": [464, 707, 597, 747], "text": "40mg+12,5mg"}]}, {"text": "Ghi ch\u00fa U\u1ed1ng:", "box": [49, 742, 235, 780], "label": "other", "words": [{"box": [49, 742, 111, 780], "text": "Ghi"}, {"box": [111, 742, 173, 780], "text": "ch\u00fa"}, {"box": [173, 742, 235, 780], "text": "U\u1ed1ng:"}]}, {"text": "S\u00e1ng 1 vi\u00ean", "box": [430, 750, 552, 780], "label": "usage", "words": [{"box": [430, 750, 470, 780], "text": "S\u00e1ng"}, {"box": [470, 750, 510, 780], "text": "1"}, {"box": [510, 750, 550, 780], "text": "vi\u00ean"}]}, {"text": "C\u1ed9ng kho\u1ea3n: 1 kho\u1ea3n", "box": [45, 792, 290, 820], "label": "other", "words": [{"box": [45, 792, 106, 820], "text": "C\u1ed9ng"}, {"box": [106, 792, 167, 820], "text": "kho\u1ea3n:"}, {"box": [167, 792, 228, 820], "text": "1"}, {"box": [228, 792, 289, 820], "text": "kho\u1ea3n"}]}, {"text": "L\u1eddi d\u1eb7n \u0111\u01a1n thu\u1ed1c: H\u1eb9n KH\u00e1m L\u1ea1i 26/8/2021", "box": [45, 825, 550, 855], "label": "other", "words": [{"box": [45, 825, 108, 855], "text": "L\u1eddi"}, {"box": [108, 825, 171, 855], "text": "d\u1eb7n"}, {"box": [171, 825, 234, 855], "text": "\u0111\u01a1n"}, {"box": [234, 825, 297, 855], "text": "thu\u1ed1c:"}, {"box": [297, 825, 360, 855], "text": "H\u1eb9n"}, {"box": [360, 825, 423, 855], "text": "KH\u00e1m"}, {"box": [423, 825, 486, 855], "text": "L\u1ea1i"}, {"box": [486, 825, 549, 855], "text": "26/8/2021"}]}, {"text": "Ng\u00e0y h\u1eb9n t\u00e1i kh\u00e1m:", "box": [45, 867, 247, 895], "label": "other", "words": [{"box": [45, 867, 95, 895], "text": "Ng\u00e0y"}, {"box": [95, 867, 145, 895], "text": "h\u1eb9n"}, {"box": [145, 867, 195, 895], "text": "t\u00e1i"}, {"box": [195, 867, 245, 895], "text": "kh\u00e1m:"}]}, {"text": "Ng\u00e0y 26/07/2021", "box": [722, 920, 925, 950], "label": "date", "words": [{"box": [722, 920, 823, 950], "text": "Ng\u00e0y"}, {"box": [823, 920, 924, 950], "text": "26/07/2021"}]}, {"text": "B\u1ec7nh nh\u00e2n k\u00fd nh\u1eadn", "box": [92, 947, 292, 975], "label": "other", "words": [{"box": [92, 947, 142, 975], "text": "B\u1ec7nh"}, {"box": [142, 947, 192, 975], "text": "nh\u00e2n"}, {"box": [192, 947, 242, 975], "text": "k\u00fd"}, {"box": [242, 947, 292, 975], "text": "nh\u1eadn"}]}, {"text": "Y, B\u00e1c s\u0129 \u0111i\u1ec1u tr\u1ecb", "box": [737, 957, 913, 990], "label": "other", "words": [{"box": [737, 957, 772, 990], "text": "Y,"}, {"box": [772, 957, 807, 990], "text": "B\u00e1c"}, {"box": [807, 957, 842, 990], "text": "s\u0129"}, {"box": [842, 957, 877, 990], "text": "\u0111i\u1ec1u"}, {"box": [877, 957, 912, 990], "text": "tr\u1ecb"}]}, {"text": "BSCKI. Tr\u1ea7n Minh Tu\u1ea5n", "box": [672, 1070, 957, 1100], "label": "other", "words": [{"box": [672, 1070, 743, 1100], "text": "BSCKI."}, {"box": [743, 1070, 814, 1100], "text": "Tr\u1ea7n"}, {"box": [814, 1070, 885, 1100], "text": "Minh"}, {"box": [885, 1070, 956, 1100], "text": "Tu\u1ea5n"}]}, {"text": "T\u00e1i kh\u00e1m xin mang theo \u0111\u01a1n, x\u00e9t nghi\u1ec7m, phim (n\u1ebfu c\u00f3)", "box": [44, 1152, 617, 1186], "label": "other", "words": [{"box": [44, 1152, 96, 1186], "text": "T\u00e1i"}, {"box": [96, 1152, 148, 1186], "text": "kh\u00e1m"}, {"box": [148, 1152, 200, 1186], "text": "xin"}, {"box": [200, 1152, 252, 1186], "text": "mang"}, {"box": [252, 1152, 304, 1186], "text": "theo"}, {"box": [304, 1152, 356, 1186], "text": "\u0111\u01a1n,"}, {"box": [356, 1152, 408, 1186], "text": "x\u00e9t"}, {"box": [408, 1152, 460, 1186], "text": "nghi\u1ec7m,"}, {"box": [460, 1152, 512, 1186], "text": "phim"}, {"box": [512, 1152, 564, 1186], "text": "(n\u1ebfu"}, {"box": [564, 1152, 616, 1186], "text": "c\u00f3)"}]}, {"text": "05/01/2022 21:58:56", "box": [877, 1215, 1089, 1240], "label": "other", "words": [{"box": [877, 1215, 983, 1240], "text": "05/01/2022"}, {"box": [983, 1215, 1089, 1240], "text": "21:58:56"}]}]}